{"ultimo":142,"hoy":12,"tickets":[{"numero":121,"escritorio":null},{"numero":122,"escritorio":null},{"numero":123,"escritorio":null},{"numero":124,"escritorio":null},{"numero":125,"escritorio":null},{"numero":126,"escritorio":null},{"numero":127,"escritorio":null},{"numero":128,"escritorio":null},{"numero":129,"escritorio":null},{"numero":130,"escritorio":null},{"numero":131,"escritorio":null},{"numero":132,"escritorio":null},{"numero":133,"escritorio":null},{"numero":134,"escritorio":null},{"numero":135,"escritorio":null},{"numero":136,"escritorio":null},{"numero":137,"escritorio":null},{"numero":138,"escritorio":null},{"numero":139,"escritorio":null},{"numero":140,"escritorio":null},{"numero":141,"escritorio":null},{"numero":142,"escritorio":null}],"ultimos4":[{"numero":120,"escritorio":"PC 3"},{"numero":119,"escritorio":"Desk 2"},{"numero":118,"escritorio":"Desk 1"},{"numero":117,"escritorio":"PC 3"}]}